sql_xml_executor/__init__.py
sql_xml_executor/executor.py
sql_xml_executor-0.5.0.dist-info/METADATA
sql_xml_executor-0.5.0.dist-info/WHEEL
sql_xml_executor-0.5.0.dist-info/top_level.txt
sql_xml_executor-0.5.0.dist-info/RECORD
